<annotation verified="yes">
  <folder>image</folder>
  <filename>c1027</filename>
  <path>C:\Users\hzs\Desktop\segmentation dataset\image\c1027.jpg</path>
  <source>
    <database>Unknown</database>
  </source>
  <size>
    <width>256</width>
    <height>256</height>
    <depth>3</depth>
  </size>
  <segmented>0</segmented>
  <object>
    <type>robndbox</type>
    <name>crack</name>
    <pose>Unspecified</pose>
    <truncated>0</truncated>
    <difficult>0</difficult>
    <robndbox>
      <cx>94.741</cx>
      <cy>193.466</cy>
      <w>15.5227</w>
      <h>70.2515</h>
      <angle>2.867438</angle>
    </robndbox>
  </object>
  <object>
    <type>robndbox</type>
    <name>crack</name>
    <pose>Unspecified</pose>
    <truncated>0</truncated>
    <difficult>0</difficult>
    <robndbox>
      <cx>90.5372</cx>
      <cy>28.2167</cy>
      <w>19.6647</w>
      <h>31.2662</h>
      <angle>0.1</angle>
    </robndbox>
  </object>
  <object>
    <type>robndbox</type>
    <name>crack</name>
    <pose>Unspecified</pose>
    <truncated>0</truncated>
    <difficult>0</difficult>
    <robndbox>
      <cx>113.2597</cx>
      <cy>77.7532</cy>
      <w>15.0</w>
      <h>36.0</h>
      <angle>0.0</angle>
    </robndbox>
  </object>
  <object>
    <type>robndbox</type>
    <name>crack</name>
    <pose>Unspecified</pose>
    <truncated>0</truncated>
    <difficult>0</difficult>
    <robndbox>
      <cx>103.5525</cx>
      <cy>125.4663</cy>
      <w>19.0254</w>
      <h>53.3337</h>
      <angle>0.3</angle>
    </robndbox>
  </object>
</annotation>