<annotation verified="yes">
  <folder>test_temp for labeling</folder>
  <filename>c2627</filename>
  <path>C:\Users\hzs\Desktop\3000dataset\total_split1\used_image\test_temp for labeling\c2627.jpg</path>
  <source>
    <database>Unknown</database>
  </source>
  <size>
    <width>256</width>
    <height>256</height>
    <depth>3</depth>
  </size>
  <segmented>0</segmented>
  <object>
    <type>robndbox</type>
    <name>crack</name>
    <pose>Unspecified</pose>
    <truncated>0</truncated>
    <difficult>0</difficult>
    <robndbox>
      <cx>145.877</cx>
      <cy>211.435</cy>
      <w>21.2327</w>
      <h>85.5613</h>
      <angle>0.030665</angle>
    </robndbox>
  </object>
  <object>
    <type>robndbox</type>
    <name>crack</name>
    <pose>Unspecified</pose>
    <truncated>0</truncated>
    <difficult>0</difficult>
    <robndbox>
      <cx>126.0246</cx>
      <cy>137.6158</cy>
      <w>18.8328</w>
      <h>74.3967</h>
      <angle>2.541593</angle>
    </robndbox>
  </object>
  <object>
    <type>robndbox</type>
    <name>crack</name>
    <pose>Unspecified</pose>
    <truncated>0</truncated>
    <difficult>0</difficult>
    <robndbox>
      <cx>110.8744</cx>
      <cy>74.756</cy>
      <w>17.5251</w>
      <h>79.2045</h>
      <angle>0.3</angle>
    </robndbox>
  </object>
  <object>
    <type>robndbox</type>
    <name>crack</name>
    <pose>Unspecified</pose>
    <truncated>0</truncated>
    <difficult>0</difficult>
    <robndbox>
      <cx>123.8</cx>
      <cy>21.0</cy>
      <w>28.0</w>
      <h>38.0</h>
      <angle>0.0</angle>
    </robndbox>
  </object>
</annotation>
