<annotation verified="yes">
  <folder>test_temp for labeling</folder>
  <filename>c2753</filename>
  <path>C:\Users\hzs\Desktop\3000dataset\total_split1\used_image\test_temp for labeling\c2753.jpg</path>
  <source>
    <database>Unknown</database>
  </source>
  <size>
    <width>256</width>
    <height>256</height>
    <depth>3</depth>
  </size>
  <segmented>0</segmented>
  <object>
    <type>robndbox</type>
    <name>crack</name>
    <pose>Unspecified</pose>
    <truncated>0</truncated>
    <difficult>0</difficult>
    <robndbox>
      <cx>93.809</cx>
      <cy>162.7365</cy>
      <w>24.2668</w>
      <h>57.9393</h>
      <angle>2.840909</angle>
    </robndbox>
  </object>
  <object>
    <type>robndbox</type>
    <name>crack</name>
    <pose>Unspecified</pose>
    <truncated>0</truncated>
    <difficult>0</difficult>
    <robndbox>
      <cx>134.3514</cx>
      <cy>230.4621</cy>
      <w>13.3919</w>
      <h>65.3953</h>
      <angle>2.194754</angle>
    </robndbox>
  </object>
  <object>
    <type>robndbox</type>
    <name>crack</name>
    <pose>Unspecified</pose>
    <truncated>0</truncated>
    <difficult>0</difficult>
    <robndbox>
      <cx>121.7677</cx>
      <cy>69.6683</cy>
      <w>22.7845</w>
      <h>141.619</h>
      <angle>0.399292</angle>
    </robndbox>
  </object>
  <object>
    <type>robndbox</type>
    <name>crack</name>
    <pose>Unspecified</pose>
    <truncated>0</truncated>
    <difficult>0</difficult>
    <robndbox>
      <cx>106.2846</cx>
      <cy>201.1648</cy>
      <w>16.3268</w>
      <h>31.921</h>
      <angle>2.841593</angle>
    </robndbox>
  </object>
</annotation>
