<annotation verified="yes">
  <folder>test_temp for labeling</folder>
  <filename>c155</filename>
  <path>C:\Users\hzs\Desktop\3000dataset\total_split1\used_image\test_temp for labeling\c155.jpg</path>
  <source>
    <database>Unknown</database>
  </source>
  <size>
    <width>256</width>
    <height>256</height>
    <depth>3</depth>
  </size>
  <segmented>0</segmented>
  <object>
    <type>robndbox</type>
    <name>crack</name>
    <pose>Unspecified</pose>
    <truncated>0</truncated>
    <difficult>0</difficult>
    <robndbox>
      <cx>149.3033</cx>
      <cy>93.2518</cy>
      <w>22.3639</w>
      <h>117.5829</h>
      <angle>0.29522</angle>
    </robndbox>
  </object>
  <object>
    <type>robndbox</type>
    <name>crack</name>
    <pose>Unspecified</pose>
    <truncated>0</truncated>
    <difficult>0</difficult>
    <robndbox>
      <cx>119.8961</cx>
      <cy>199.2532</cy>
      <w>16.8519</w>
      <h>107.8565</h>
      <angle>0.1</angle>
    </robndbox>
  </object>
  <object>
    <type>robndbox</type>
    <name>crack</name>
    <pose>Unspecified</pose>
    <truncated>0</truncated>
    <difficult>0</difficult>
    <robndbox>
      <cx>164.9</cx>
      <cy>24.5</cy>
      <w>13.0</w>
      <h>43.0</h>
      <angle>0.0</angle>
    </robndbox>
  </object>
</annotation>
