<annotation verified="yes">
  <folder>temp2</folder>
  <filename>c2493</filename>
  <path>C:\Users\hzs\Desktop\Mask DO-YOLOv4 &#25968;&#25454;&#38598;\temp2\c2493.png</path>
  <source>
    <database>Unknown</database>
  </source>
  <size>
    <width>256</width>
    <height>256</height>
    <depth>3</depth>
  </size>
  <segmented>0</segmented>
  <object>
    <type>robndbox</type>
    <name>crack</name>
    <pose>Unspecified</pose>
    <truncated>0</truncated>
    <difficult>0</difficult>
    <robndbox>
      <cx>128.4014</cx>
      <cy>86.0898</cy>
      <w>18.4763</w>
      <h>92.8771</h>
      <angle>3.01564</angle>
    </robndbox>
  </object>
  <object>
    <type>robndbox</type>
    <name>crack</name>
    <pose>Unspecified</pose>
    <truncated>0</truncated>
    <difficult>0</difficult>
    <robndbox>
      <cx>120.1252</cx>
      <cy>176.3374</cy>
      <w>19.3546</w>
      <h>93.072</h>
      <angle>0.1</angle>
    </robndbox>
  </object>
  <object>
    <type>robndbox</type>
    <name>crack</name>
    <pose>Unspecified</pose>
    <truncated>0</truncated>
    <difficult>0</difficult>
    <robndbox>
      <cx>117.4424</cx>
      <cy>238.3766</cy>
      <w>13.7548</w>
      <h>35.2468</h>
      <angle>0.0</angle>
    </robndbox>
  </object>
  <object>
    <type>robndbox</type>
    <name>crack</name>
    <pose>Unspecified</pose>
    <truncated>0</truncated>
    <difficult>0</difficult>
    <robndbox>
      <cx>144.348</cx>
      <cy>24.008</cy>
      <w>49.8446</w>
      <h>17.5966</h>
      <angle>2.341593</angle>
    </robndbox>
  </object>
</annotation>
