<annotation verified="yes">
  <folder>test_temp for labeling</folder>
  <filename>c371</filename>
  <path>C:\Users\hzs\Desktop\3000dataset\total_split1\used_image\test_temp for labeling\c371.jpg</path>
  <source>
    <database>Unknown</database>
  </source>
  <size>
    <width>256</width>
    <height>256</height>
    <depth>3</depth>
  </size>
  <segmented>0</segmented>
  <object>
    <type>robndbox</type>
    <name>crack</name>
    <pose>Unspecified</pose>
    <truncated>0</truncated>
    <difficult>0</difficult>
    <robndbox>
      <cx>97.5331</cx>
      <cy>158.0924</cy>
      <w>18.239</w>
      <h>118.3059</h>
      <angle>0.659398</angle>
    </robndbox>
  </object>
  <object>
    <type>robndbox</type>
    <name>crack</name>
    <pose>Unspecified</pose>
    <truncated>0</truncated>
    <difficult>0</difficult>
    <robndbox>
      <cx>82.337</cx>
      <cy>229.2542</cy>
      <w>14.2351</w>
      <h>57.557</h>
      <angle>2.413525</angle>
    </robndbox>
  </object>
  <object>
    <type>robndbox</type>
    <name>crack</name>
    <pose>Unspecified</pose>
    <truncated>0</truncated>
    <difficult>0</difficult>
    <robndbox>
      <cx>168.5649</cx>
      <cy>38.5</cy>
      <w>20.0</w>
      <h>77.0</h>
      <angle>0.0</angle>
    </robndbox>
  </object>
  <object>
    <type>robndbox</type>
    <name>crack</name>
    <pose>Unspecified</pose>
    <truncated>0</truncated>
    <difficult>0</difficult>
    <robndbox>
      <cx>115.1824</cx>
      <cy>93.3766</cy>
      <w>14.7649</w>
      <h>67.2468</h>
      <angle>0.0</angle>
    </robndbox>
  </object>
  <object>
    <type>robndbox</type>
    <name>crack</name>
    <pose>Unspecified</pose>
    <truncated>0</truncated>
    <difficult>0</difficult>
    <robndbox>
      <cx>152.0726</cx>
      <cy>95.3539</cy>
      <w>60.6738</w>
      <h>22.3531</h>
      <angle>2.541593</angle>
    </robndbox>
  </object>
</annotation>
