<annotation verified="yes">
  <folder>manual recognized2</folder>
  <filename>w134p14</filename>
  <path>E:\何增胜\大学生创新项目\20220708【大创课题数据集标注资料】\20230228_label selecting\manual recognized2\w134p14.jpg</path>
  <source>
    <database>Unknown</database>
  </source>
  <size>
    <width>256</width>
    <height>256</height>
    <depth>3</depth>
  </size>
  <segmented>0</segmented>
  <object>
    <type>robndbox</type>
    <name>pothole</name>
    <pose>Unspecified</pose>
    <truncated>0</truncated>
    <difficult>0</difficult>
    <robndbox>
      <cx>127.50709999999998</cx>
      <cy>128.8872</cy>
      <w>70.4999</w>
      <h>37.6428</h>
      <angle>0.29999960000000003</angle>
    </robndbox>
  </object>
</annotation>