<annotation verified="yes">
  <folder>added</folder>
  <filename>w12p23</filename>
  <path>C:\Users\hzs\Desktop\Mask DO-YOLOv4 数据集\added\w12p23.jpg</path>
  <source>
    <database>Unknown</database>
  </source>
  <size>
    <width>652</width>
    <height>489</height>
    <depth>3</depth>
  </size>
  <segmented>0</segmented>
  <object>
    <type>robndbox</type>
    <name>crack</name>
    <pose>Unspecified</pose>
    <truncated>0</truncated>
    <difficult>0</difficult>
    <robndbox>
      <cx>128.5045</cx>
      <cy>128.5235</cy>
      <w>18.2684</w>
      <h>86.3744</h>
      <angle>0.2</angle>
    </robndbox>
  </object>
</annotation>