<annotation verified="yes">
  <folder>manual recognized1</folder>
  <filename>w130p351</filename>
  <path>E:\何增胜\大学生创新项目\20220708【大创课题数据集标注资料】\20230228_label selecting\manual recognized1\w130p351.jpg</path>
  <source>
    <database>Unknown</database>
  </source>
  <size>
    <width>431</width>
    <height>418</height>
    <depth>3</depth>
  </size>
  <segmented>0</segmented>
  <object>
    <type>robndbox</type>
    <name>pothole</name>
    <pose>Unspecified</pose>
    <truncated>0</truncated>
    <difficult>0</difficult>
    <robndbox>
      <cx>52.435900000000004</cx>
      <cy>190.0983</cy>
      <w>95.0</w>
      <h>19.0</h>
      <angle>0.0</angle>
    </robndbox>
  </object>
  <object>
    <type>robndbox</type>
    <name>pothole</name>
    <pose>Unspecified</pose>
    <truncated>0</truncated>
    <difficult>0</difficult>
    <robndbox>
      <cx>217.4359</cx>
      <cy>184.0983</cy>
      <w>81.0</w>
      <h>17.0</h>
      <angle>0.0</angle>
    </robndbox>
  </object>
  <object>
    <type>robndbox</type>
    <name>pothole</name>
    <pose>Unspecified</pose>
    <truncated>0</truncated>
    <difficult>0</difficult>
    <robndbox>
      <cx>398.4359</cx>
      <cy>179.5983</cy>
      <w>59.0</w>
      <h>12.0</h>
      <angle>0.0</angle>
    </robndbox>
  </object>
</annotation>