<annotation verified="yes">
  <folder>added</folder>
  <filename>w3p15</filename>
  <path>C:\Users\hzs\Desktop\Mask DO-YOLOv4 数据集\added\w3p15.png</path>
  <source>
    <database>Unknown</database>
  </source>
  <size>
    <width>555</width>
    <height>417</height>
    <depth>3</depth>
  </size>
  <segmented>0</segmented>
  <object>
    <type>robndbox</type>
    <name>breakage</name>
    <pose>Unspecified</pose>
    <truncated>0</truncated>
    <difficult>0</difficult>
    <robndbox>
      <cx>128.44420000000002</cx>
      <cy>128.0318</cy>
      <w>77.6875</w>
      <h>40.8345</h>
      <angle>0.3</angle>
    </robndbox>
  </object>
</annotation>